smserver-1.0.0.data/scripts/smserver
smserver/ability.py
smserver/authplugin.py
smserver/server.py
smserver/pluginmanager.py
smserver/stepmania_controller.py
smserver/__init__.py
smserver/chatplugin.py
smserver/chathelper.py
smserver/database.py
smserver/conf.py
smserver/logger.py
smserver/watcher.py
smserver/sdnotify.py
smserver/_fallback_conf/conf.yml.orig
smserver/chat_commands/__init__.py
smserver/chat_commands/general.py
smserver/chat_commands/ban.py
smserver/chat_commands/role.py
smserver/chat_commands/room_update.py
smserver/auth/__init__.py
smserver/auth/database.py
smserver/controllers/request_start_game.py
smserver/controllers/login.py
smserver/controllers/user_screen.py
smserver/controllers/create_room.py
smserver/controllers/__init__.py
smserver/controllers/hello.py
smserver/controllers/chat.py
smserver/controllers/discovery.py
smserver/controllers/game_status_update.py
smserver/controllers/enter_room.py
smserver/controllers/room_info.py
smserver/controllers/game_over.py
smserver/controllers/user_profil.py
smserver/controllers/game_start_request.py
smserver/controllers/smo.py
smserver/plugins/__init__.py
smserver/plugins/example/plugin.py
smserver/plugins/example/__init__.py
smserver/plugins/hardcore/plugin.py
smserver/plugins/hardcore/__init__.py
smserver/smutils/__init__.py
smserver/smutils/smthread.py
smserver/smutils/smattack.py
smserver/smutils/smpacket.py
smserver/smutils/smconn.py
smserver/smutils/smconnections/udpsocket.py
smserver/smutils/smconnections/__init__.py
smserver/smutils/smconnections/websocket.py
smserver/smutils/smconnections/smtcpsocket.py
smserver/smutils/smconnections/asynctcpserver.py
smserver/models/song.py
smserver/models/__init__.py
smserver/models/song_stat.py
smserver/models/privilege.py
smserver/models/ban.py
smserver/models/schema.py
smserver/models/room.py
smserver/models/user.py
smserver/models/game.py
etc/smserver/conf.yml.orig
smserver-1.0.0.dist-info/metadata.json
smserver-1.0.0.dist-info/top_level.txt
smserver-1.0.0.dist-info/DESCRIPTION.rst
smserver-1.0.0.dist-info/METADATA
smserver-1.0.0.dist-info/RECORD
smserver-1.0.0.dist-info/WHEEL
