Metadata-Version: 2.0
Name: smserver
Version: 1.0.0
Summary: An implementation of a Stepmania server
Home-page: http://github.com/ningirsu/stepmania-server
Author: Sélim Menouar
Author-email: selim.menouar@rez-gif.supelec.fr
License: MIT
Platform: UNKNOWN
Classifier: Programming Language :: Python
Classifier: Development Status :: 5 - Production/Stable
Classifier: License :: OSI Approved :: MIT License
Classifier: Topic :: Games/Entertainment
Classifier: Topic :: Games/Entertainment :: Arcade
Classifier: Operating System :: OS Independent
Classifier: Programming Language :: Python :: 3 :: Only
Classifier: Programming Language :: Python :: 3.3
Classifier: Programming Language :: Python :: 3.4
Classifier: Programming Language :: Python :: 3.5
Requires-Dist: pyyaml
Requires-Dist: sqlalchemy
Requires-Dist: websockets
Requires-Dist: asyncio; python_version=="3.3"
Requires-Dist: enum34; python_version=="3.3"
